sphinx_press_autodoc_theme/__init__.py
sphinx_press_autodoc_theme/genindex.html
sphinx_press_autodoc_theme/layout.html
sphinx_press_autodoc_theme/page.html
sphinx_press_autodoc_theme/search.html
sphinx_press_autodoc_theme/theme.conf
sphinx_press_autodoc_theme/util/extlinks.html
sphinx_press_autodoc_theme/util/footer.html
sphinx_press_autodoc_theme/util/linktags.html
sphinx_press_autodoc_theme/util/navbar.html
sphinx_press_autodoc_theme/util/navlinks.html
sphinx_press_autodoc_theme/util/pagenav.html
sphinx_press_autodoc_theme/util/sidetoc.html
sphinx_press_autodoc_theme-0.1.0a2.dist-info/DESCRIPTION.rst
sphinx_press_autodoc_theme-0.1.0a2.dist-info/METADATA
sphinx_press_autodoc_theme-0.1.0a2.dist-info/RECORD
sphinx_press_autodoc_theme-0.1.0a2.dist-info/WHEEL
sphinx_press_autodoc_theme-0.1.0a2.dist-info/entry_points.txt
sphinx_press_autodoc_theme-0.1.0a2.dist-info/metadata.json
sphinx_press_autodoc_theme-0.1.0a2.dist-info/top_level.txt
sphinx_press_theme/__init__.py
sphinx_press_theme/genindex.html
sphinx_press_theme/layout.html
sphinx_press_theme/page.html
sphinx_press_theme/search.html
sphinx_press_theme/theme.conf
sphinx_press_theme/util/extlinks.html
sphinx_press_theme/util/footer.html
sphinx_press_theme/util/linktags.html
sphinx_press_theme/util/navbar.html
sphinx_press_theme/util/navlinks.html
sphinx_press_theme/util/pagenav.html
sphinx_press_theme/util/sidetoc.html
