Metadata-Version: 2.0
Name: sphinx-press-autodoc-theme
Version: 0.1.0a2
Summary: A fork of Eduardo Naufel Schettino's sphinx_press_theme, with support for sphinx.ext.autodoc
Home-page: https://chris104957.github.io/sphinx_press_site/
Author: Christopher Davies
Author-email: UNKNOWN
License: MIT
Keywords: sphinx doc theme vue.js
Platform: UNKNOWN
Classifier: Framework :: Sphinx
Classifier: Framework :: Sphinx :: Theme
Classifier: Development Status :: 3 - Alpha
Classifier: License :: OSI Approved :: MIT License
Classifier: Environment :: Console
Classifier: Environment :: Web Environment
Classifier: Intended Audience :: Developers
Classifier: Programming Language :: Python :: 3
Classifier: Programming Language :: Python :: 3.5
Classifier: Programming Language :: Python :: 3.6
Classifier: Programming Language :: Python :: 3.7
Classifier: Operating System :: OS Independent
Classifier: Topic :: Documentation
Classifier: Topic :: Software Development :: Documentation
Requires-Dist: sphinx
